aibox/nlp/__init__.py
aibox/nlp/cache/__init__.py
aibox/nlp/cache/features.py
aibox/nlp/cache/mixed_feature_cache.py
aibox/nlp/cache/vectorizers.py
aibox/nlp/core/__init__.py
aibox/nlp/core/dataset.py
aibox/nlp/core/estimator.py
aibox/nlp/core/experiment.py
aibox/nlp/core/feature_extractor.py
aibox/nlp/core/metric.py
aibox/nlp/core/pipeline.py
aibox/nlp/core/vectorizer.py
aibox/nlp/data/__init__.py
aibox/nlp/data/corpus/__init__.py
aibox/nlp/data/datasets/__init__.py
aibox/nlp/data/datasets/dataset_df.py
aibox/nlp/data/datasets/essay_br.py
aibox/nlp/data/datasets/portuguese_narrative_essays.py
aibox/nlp/data/datasets/utils.py
aibox/nlp/estimators/__init__.py
aibox/nlp/estimators/sklearn_estimator.py
aibox/nlp/estimators/classification/__init__.py
aibox/nlp/estimators/classification/adaboost_classifier.py
aibox/nlp/estimators/classification/catboost_classifier.py
aibox/nlp/estimators/classification/extra_trees_classifier.py
aibox/nlp/estimators/classification/gaussian_nb.py
aibox/nlp/estimators/classification/kn_classifier.py
aibox/nlp/estimators/classification/lgbm_classifier.py
aibox/nlp/estimators/classification/lstm_classifier.py
aibox/nlp/estimators/classification/mlp_classifier.py
aibox/nlp/estimators/classification/random_forest_classifier.py
aibox/nlp/estimators/classification/svm.py
aibox/nlp/estimators/classification/transformer_classifier.py
aibox/nlp/estimators/classification/xgboost_classifier.py
aibox/nlp/estimators/generic/__init__.py
aibox/nlp/estimators/generic/lstm.py
aibox/nlp/estimators/generic/mlp.py
aibox/nlp/estimators/generic/transformers.py
aibox/nlp/estimators/regression/__init__.py
aibox/nlp/estimators/regression/adaboost_regressor.py
aibox/nlp/estimators/regression/catboost_regressor.py
aibox/nlp/estimators/regression/extra_trees_regressor.py
aibox/nlp/estimators/regression/kn_regressor.py
aibox/nlp/estimators/regression/lgbm_regressor.py
aibox/nlp/estimators/regression/lstm_regressor.py
aibox/nlp/estimators/regression/mlp_regressor.py
aibox_nlp-0.5.0.dist-info/licenses/LICENSE
aibox_nlp-0.5.0.dist-info/METADATA
aibox_nlp-0.5.0.dist-info/WHEEL
aibox_nlp-0.5.0.dist-info/top_level.txt
aibox_nlp-0.5.0.dist-info/RECORD
