Metadata-Version: 2.4
Name: aibox-nlp
Version: 0.5.0
Summary: AiBox Natural Language Processing Toolkit.
Author: AiBox Lab
Maintainer-email: Moésio Filho <moesio.f@gmail.com>
Project-URL: Homepage, https://aiboxlab.org/nlp/
Project-URL: Documentation, https://aiboxlab.org/nlp/
Project-URL: Repository, https://github.com/aiboxlab/nlp.git
Project-URL: Issues, https://github.com/aiboxlab/nlp/issues
Project-URL: Changelog, https://github.com/aiboxlab/nlp/blob/main/CHANGELOG.md
Classifier: Programming Language :: Python :: 3.10
Classifier: Programming Language :: Python :: 3.11
Classifier: Development Status :: 3 - Alpha
Requires-Python: >=3.10
License-File: LICENSE
Requires-Dist: importlib-resources>=5.0; python_full_version < "3.9"
Requires-Dist: joblib>=1.4.0
Requires-Dist: kagglehub>=0.3.0
Requires-Dist: nltk>=3.8.1
Requires-Dist: numpy>=1.23.2
Requires-Dist: pandas>=2.0.0
Requires-Dist: platformdirs>=4.0.0
Requires-Dist: scikit-learn>=1.3.2
Requires-Dist: scipy<1.13.0,>=1.11.4
Requires-Dist: spacy>=3.7.0
Requires-Dist: torch>=2.5.0
Requires-Dist: tqdm>=4.66.0
Provides-Extra: br
Requires-Dist: cogroo4py>=0.5.0; extra == "br"
Requires-Dist: cohmetrix-br-lib>=0.1.5; extra == "br"
Requires-Dist: fuzzysearch>=0.7.0; extra == "br"
Requires-Dist: fuzzywuzzy>=0.18.0; extra == "br"
Requires-Dist: gensim>=4.3.0; extra == "br"
Requires-Dist: kenlm>=0.3.0; extra == "br"
Requires-Dist: language-tool-python>=2.7.0; extra == "br"
Requires-Dist: lexical-diversity>=0.1.0; extra == "br"
Requires-Dist: polyfuzz>=0.4.0; extra == "br"
Requires-Dist: py-rouge==1.1; extra == "br"
Requires-Dist: pyspellchecker>=0.7.0; extra == "br"
Requires-Dist: python-levenshtein>=0.21.0; extra == "br"
Requires-Dist: trunajod>=0.1.0; extra == "br"
Requires-Dist: unidecode>=1.3.7; extra == "br"
Requires-Dist: pip>=25.2; extra == "br"
Provides-Extra: embeddings
Requires-Dist: fasttext>=0.9.2; extra == "embeddings"
Requires-Dist: accelerate>=0.26.0; extra == "embeddings"
Requires-Dist: datasets>=3.1.0; extra == "embeddings"
Requires-Dist: sentence-transformers>=3.3.0; extra == "embeddings"
Requires-Dist: torchvision>=0.20; extra == "embeddings"
Requires-Dist: transformers>=4.46.1; extra == "embeddings"
Provides-Extra: trees
Requires-Dist: catboost>=1.2.2; extra == "trees"
Requires-Dist: lightgbm>=4.2.0; extra == "trees"
Requires-Dist: xgboost>=2.0.3; extra == "trees"
Provides-Extra: all
Requires-Dist: aibox-nlp[br,embeddings,trees]; extra == "all"
Dynamic: license-file
